metatool/__init__.py
metatool/config.py
metatool/core.py
metatool/schemas.py
metatool/storage/__init__.py
metatool/storage/api_storage.py
metatool/storage/base.py
metatool/storage/sqlite_storage.py
metatool-0.0.1.dist-info/LICENSE
metatool-0.0.1.dist-info/METADATA
metatool-0.0.1.dist-info/WHEEL
metatool-0.0.1.dist-info/top_level.txt
metatool-0.0.1.dist-info/RECORD
