Metadata-Version: 2.1
Name: metatool
Version: 0.0.1
Summary: A Python interface for metatool functionality
Author: James Zhang
Requires-Python: >=3.9
License-File: LICENSE
Requires-Dist: langchain
Requires-Dist: langchain-core
Requires-Dist: langchain-community
Requires-Dist: langchain-openai
Requires-Dist: pydantic
Requires-Dist: open-interpreter
Requires-Dist: uuid
